03-Encoder-Decoder/rtl/bcd_to_7segment.v
module bcd_to_7segment(
    input [3:0] BCD,
    output reg [6:0] SEG
);

always @(*) begin
    case (BCD)
        4'b0000: SEG = 7'b1111110; // 0
        4'b0001: SEG = 7'b0110000; // 1
        4'b0010: SEG = 7'b1101101; // 2
        4'b0011: SEG = 7'b1111001; // 3
        4'b0100: SEG = 7'b0110011; // 4
        4'b0101: SEG = 7'b1011011; // 5
        4'b0110: SEG = 7'b1011111; // 6
        4'b0111: SEG = 7'b1110000; // 7
        4'b1000: SEG = 7'b1111111; // 8
        4'b1001: SEG = 7'b1111011; // 9
        default: SEG = 7'b0000000;
    endcase
end

endmodule

03-Encoder-Decoder/tb/bcd_to_7segment_tb.v
`timescale 1ns/1ps

module bcd_to_7segment_tb;

reg [3:0] BCD;
wire [6:0] SEG;

bcd_to_7segment uut (
    .BCD(BCD),
    .SEG(SEG)
);

initial begin

    $dumpfile("bcd_to_7segment.vcd");
    $dumpvars(0, bcd_to_7segment_tb);

    BCD = 4'b0000; #10; // 0
    BCD = 4'b0001; #10; // 1
    BCD = 4'b0010; #10; // 2
    BCD = 4'b0011; #10; // 3
    BCD = 4'b0100; #10; // 4
    BCD = 4'b0101; #10; // 5
    BCD = 4'b0110; #10; // 6
    BCD = 4'b0111; #10; // 7
    BCD = 4'b1000; #10; // 8
    BCD = 4'b1001; #10; // 9

    $finish;

end

endmodule

bcd_to_7segment.vcd
$date
	Fri Jul 31 21:17:33 2026
$end
$version
	Icarus Verilog
$end
$timescale
	1ps
$end
$scope module bcd_to_7segment_tb $end
$var wire 7 ! SEG [6:0] $end
$var reg 4 " BCD [3:0] $end
$scope module uut $end
$var wire 4 # BCD [3:0] $end
$var reg 7 $ SEG [6:0] $end
$upscope $end
$upscope $end
$enddefinitions $end
#0
$dumpvars
b1111110 $
b0 #
b0 "
b1111110 !
$end
#10000
b110000 !
b110000 $
b1 "
b1 #
#20000
b1101101 !
b1101101 $
b10 "
b10 #
#30000
b1111001 !
b1111001 $
b11 "
b11 #
#40000
b110011 !
b110011 $
b100 "
b100 #
#50000
b1011011 !
b1011011 $
b101 "
b101 #
#60000
b1011111 !
b1011111 $
b110 "
b110 #
#70000
b1110000 !
b1110000 $
b111 "
b111 #
#80000
b1111111 !
b1111111 $
b1000 "
b1000 #
#90000
b1111011 !
b1111011 $
b1001 "
b1001 #
