03-Encoder-Decoder/rtl/binary_to_gray.v
module binary_to_gray(
    input  [3:0] binary,
    output [3:0] gray
);

assign gray[3] = binary[3];
assign gray[2] = binary[3] ^ binary[2];
assign gray[1] = binary[2] ^ binary[1];
assign gray[0] = binary[1] ^ binary[0];

endmodule

03-Encoder-Decoder/tb/binary_to_gray_tb.v
`timescale 1ns/1ps

module binary_to_gray_tb;

reg [3:0] binary;
wire [3:0] gray;

binary_to_gray uut (
    .binary(binary),
    .gray(gray)
);

initial begin

    $dumpfile("binary_to_gray.vcd");
    $dumpvars(0, binary_to_gray_tb);

    binary = 4'b0000; #10;
    binary = 4'b0001; #10;
    binary = 4'b0010; #10;
    binary = 4'b0011; #10;
    binary = 4'b0100; #10;
    binary = 4'b0101; #10;
    binary = 4'b0110; #10;
    binary = 4'b0111; #10;
    binary = 4'b1000; #10;
    binary = 4'b1001; #10;
    binary = 4'b1010; #10;
    binary = 4'b1011; #10;
    binary = 4'b1100; #10;
    binary = 4'b1101; #10;
    binary = 4'b1110; #10;
    binary = 4'b1111; #10;

    $finish;

end

endmodule

binary_to_gray.vcd
$date
	Fri Jul 31 21:41:33 2026
$end
$version
	Icarus Verilog
$end
$timescale
	1ps
$end
$scope module binary_to_gray_tb $end
$var wire 4 ! gray [3:0] $end
$var reg 4 " binary [3:0] $end
$scope module uut $end
$var wire 4 # binary [3:0] $end
$var wire 4 $ gray [3:0] $end
$upscope $end
$upscope $end
$enddefinitions $end
#0
$dumpvars
b0 $
b0 #
b0 "
b0 !
$end
#10000
b1 !
b1 $
b1 "
b1 #
#20000
b11 !
b11 $
b10 "
b10 #
#30000
b10 !
b10 $
b11 "
b11 #
#40000
b110 !
b110 $
b100 "
b100 #
#50000
b111 !
b111 $
b101 "
b101 #
#60000
b101 !
b101 $
b110 "
b110 #
#70000
b100 !
b100 $
b111 "
b111 #
#80000
b1100 !
b1100 $
b1000 "
b1000 #
#90000
b1101 !
b1101 $
b1001 "
b1001 #
#100000
b1111 !
b1111 $
b1010 "
b1010 #
#110000
b1110 !
b1110 $
b1011 "
b1011 #
#120000
b1010 !
b1010 $
b1100 "
b1100 #
#130000
b1011 !
b1011 $
b1101 "
b1101 #
#140000
b1001 !
b1001 $
b1110 "
b1110 #
#150000
b1000 !
b1000 $
b1111 "
b1111 #
