03-Encoder-Decoder/rtl/decoder3to8.v
module decoder3to8(
    input A,
    input B,
    input C,
    output Y0,
    output Y1,
    output Y2,
    output Y3,
    output Y4,
    output Y5,
    output Y6,
    output Y7
);

assign Y0 = ~A & ~B & ~C;
assign Y1 = ~A & ~B &  C;
assign Y2 = ~A &  B & ~C;
assign Y3 = ~A &  B &  C;
assign Y4 =  A & ~B & ~C;
assign Y5 =  A & ~B &  C;
assign Y6 =  A &  B & ~C;
assign Y7 =  A &  B &  C;

endmodule

03-Encoder-Decoder/tb/decoder3to8_tb.v
`timescale 1ns/1ps

module decoder3to8_tb;

reg A, B, C;

wire Y0, Y1, Y2, Y3, Y4, Y5, Y6, Y7;

decoder3to8 uut(
    .A(A),
    .B(B),
    .C(C),
    .Y0(Y0),
    .Y1(Y1),
    .Y2(Y2),
    .Y3(Y3),
    .Y4(Y4),
    .Y5(Y5),
    .Y6(Y6),
    .Y7(Y7)
);

initial begin

    $dumpfile("decoder3to8.vcd");
    $dumpvars(0, decoder3to8_tb);

    $display("A B C | Y0 Y1 Y2 Y3 Y4 Y5 Y6 Y7");

    $monitor("%b %b %b | %b %b %b %b %b %b %b %b",
             A,B,C,
             Y0,Y1,Y2,Y3,Y4,Y5,Y6,Y7);

    A=0; B=0; C=0; #10;
    A=0; B=0; C=1; #10;
    A=0; B=1; C=0; #10;
    A=0; B=1; C=1; #10;
    A=1; B=0; C=0; #10;
    A=1; B=0; C=1; #10;
    A=1; B=1; C=0; #10;
    A=1; B=1; C=1; #10;

    $finish;

end

endmodule

decoder3to8.vcd
$date
	Wed Jul 29 21:40:16 2026
$end
$version
	Icarus Verilog
$end
$timescale
	1ps
$end
$scope module decoder3to8_tb $end
$var wire 1 ! Y7 $end
$var wire 1 " Y6 $end
$var wire 1 # Y5 $end
$var wire 1 $ Y4 $end
$var wire 1 % Y3 $end
$var wire 1 & Y2 $end
$var wire 1 ' Y1 $end
$var wire 1 ( Y0 $end
$var reg 1 ) A $end
$var reg 1 * B $end
$var reg 1 + C $end
$scope module uut $end
$var wire 1 ) A $end
$var wire 1 * B $end
$var wire 1 + C $end
$var wire 1 ( Y0 $end
$var wire 1 ' Y1 $end
$var wire 1 & Y2 $end
$var wire 1 % Y3 $end
$var wire 1 $ Y4 $end
$var wire 1 # Y5 $end
$var wire 1 " Y6 $end
$var wire 1 ! Y7 $end
$upscope $end
$upscope $end
$enddefinitions $end
#0
$dumpvars
0+
0*
0)
1(
0'
0&
0%
0$
0#
0"
0!
$end
#10000
0(
1'
1+
#20000
1&
0'
0+
1*
#30000
0&
1%
1+
#40000
1$
0%
0+
0*
1)
#50000
0$
1#
1+
#60000
1"
0#
0+
1*
#70000
0"
1!
1+
