02-Multiplexer/rtl/demux1to8.v
module demux1to8(
    input I,
    input S2,
    input S1,
    input S0,
    output Y0,
    output Y1,
    output Y2,
    output Y3,
    output Y4,
    output Y5,
    output Y6,
    output Y7
);

assign Y0 = (~S2 & ~S1 & ~S0) ? I : 1'b0;
assign Y1 = (~S2 & ~S1 &  S0) ? I : 1'b0;
assign Y2 = (~S2 &  S1 & ~S0) ? I : 1'b0;
assign Y3 = (~S2 &  S1 &  S0) ? I : 1'b0;
assign Y4 = ( S2 & ~S1 & ~S0) ? I : 1'b0;
assign Y5 = ( S2 & ~S1 &  S0) ? I : 1'b0;
assign Y6 = ( S2 &  S1 & ~S0) ? I : 1'b0;
assign Y7 = ( S2 &  S1 &  S0) ? I : 1'b0;

endmodule

02-Multiplexer/tb/demux1to8_tb.v
`timescale 1ns/1ps

module demux1to8_tb;

reg I;
reg S2, S1, S0;

wire Y0, Y1, Y2, Y3, Y4, Y5, Y6, Y7;

demux1to8 uut(
    .I(I),
    .S2(S2),
    .S1(S1),
    .S0(S0),
    .Y0(Y0),
    .Y1(Y1),
    .Y2(Y2),
    .Y3(Y3),
    .Y4(Y4),
    .Y5(Y5),
    .Y6(Y6),
    .Y7(Y7)
);

initial begin

    $dumpfile("demux1to8.vcd");
    $dumpvars(0, demux1to8_tb);

    $display("I S2 S1 S0 | Y0 Y1 Y2 Y3 Y4 Y5 Y6 Y7");
    $monitor("%b %b  %b  %b | %b  %b  %b  %b  %b  %b  %b  %b",
             I,S2,S1,S0,
             Y0,Y1,Y2,Y3,Y4,Y5,Y6,Y7);

    I=1; S2=0; S1=0; S0=0; #10;
    I=1; S2=0; S1=0; S0=1; #10;
    I=1; S2=0; S1=1; S0=0; #10;
    I=1; S2=0; S1=1; S0=1; #10;
    I=1; S2=1; S1=0; S0=0; #10;
    I=1; S2=1; S1=0; S0=1; #10;
    I=1; S2=1; S1=1; S0=0; #10;
    I=1; S2=1; S1=1; S0=1; #10;

    I=0; S2=0; S1=0; S0=0; #10;

    $finish;

end

endmodule

demux1to8.vcd
$date
	Mon Jul 27 00:54:01 2026
$end
$version
	Icarus Verilog
$end
$timescale
	1ps
$end
$scope module demux1to8_tb $end
$var wire 1 ! Y7 $end
$var wire 1 " Y6 $end
$var wire 1 # Y5 $end
$var wire 1 $ Y4 $end
$var wire 1 % Y3 $end
$var wire 1 & Y2 $end
$var wire 1 ' Y1 $end
$var wire 1 ( Y0 $end
$var reg 1 ) I $end
$var reg 1 * S0 $end
$var reg 1 + S1 $end
$var reg 1 , S2 $end
$scope module uut $end
$var wire 1 ) I $end
$var wire 1 * S0 $end
$var wire 1 + S1 $end
$var wire 1 , S2 $end
$var wire 1 ! Y7 $end
$var wire 1 " Y6 $end
$var wire 1 # Y5 $end
$var wire 1 $ Y4 $end
$var wire 1 % Y3 $end
$var wire 1 & Y2 $end
$var wire 1 ' Y1 $end
$var wire 1 ( Y0 $end
$upscope $end
$upscope $end
$enddefinitions $end
#0
$dumpvars
0,
0+
0*
1)
1(
0'
0&
0%
0$
0#
0"
0!
$end
#10000
0(
1'
1*
#20000
1&
0'
0*
1+
#30000
0&
1%
1*
#40000
1$
0%
0*
0+
1,
#50000
0$
1#
1*
#60000
1"
0#
0*
1+
#70000
0"
1!
1*
#80000
0!
0*
0+
0,
0)
