02-Multiplexer/rtl/mux2to1.v
module mux2to1 (
    input A,
    input B,
    input S,
    output Y
);

assign Y = S ? B : A;

endmodule

02-Multiplexer/tb/mux2to1_tb.v
`timescale 1ns/1ps

module mux2to1_tb;

reg A, B, S;
wire Y;

mux2to1 uut (
    .A(A),
    .B(B),
    .S(S),
    .Y(Y)
);

initial begin
    $dumpfile("mux2to1.vcd");
    $dumpvars(0, mux2to1_tb);

    $display("S A B | Y");
    $monitor("%b %b %b | %b", S, A, B, Y);

    S = 0; A = 0; B = 0;
    #10 S = 0; A = 0; B = 1;
    #10 S = 0; A = 1; B = 0;
    #10 S = 0; A = 1; B = 1;

    #10 S = 1; A = 0; B = 0;
    #10 S = 1; A = 0; B = 1;
    #10 S = 1; A = 1; B = 0;
    #10 S = 1; A = 1; B = 1;

    #10 $finish;
end

endmodule

mux2to1.vcd
$date
	Sun Jul 26 00:08:25 2026
$end
$version
	Icarus Verilog
$end
$timescale
	1ps
$end
$scope module mux2to1_tb $end
$var wire 1 ! Y $end
$var reg 1 " A $end
$var reg 1 # B $end
$var reg 1 $ S $end
$scope module uut $end
$var wire 1 " A $end
$var wire 1 # B $end
$var wire 1 $ S $end
$var wire 1 ! Y $end
$upscope $end
$upscope $end
$enddefinitions $end
#0
$dumpvars
0$
0#
0"
0!
$end
#10000
1#
#20000
1!
0#
1"
#30000
1#
#40000
0!
0#
0"
1$
#50000
1!
1#
#60000
0!
0#
1"
#70000
1!
1#
