02-Multiplexer/rtl/mux8to1.v

module mux8to1 (
    input I0,
    input I1,
    input I2,
    input I3,
    input I4,
    input I5,
    input I6,
    input I7,
    input S2,
    input S1,
    input S0,
    output reg Y
);

always @(*) begin
    case ({S2, S1, S0})
        3'b000: Y = I0;
        3'b001: Y = I1;
        3'b010: Y = I2;
        3'b011: Y = I3;
        3'b100: Y = I4;
        3'b101: Y = I5;
        3'b110: Y = I6;
        3'b111: Y = I7;
        default: Y = 1'b0;
    endcase
end

endmodule

02-Multiplexer/tb/mux8to1_tb.v
`timescale 1ns/1ps

module mux8to1_tb;

reg I0, I1, I2, I3, I4, I5, I6, I7;
reg S2, S1, S0;
wire Y;

mux8to1 uut (
    .I0(I0),
    .I1(I1),
    .I2(I2),
    .I3(I3),
    .I4(I4),
    .I5(I5),
    .I6(I6),
    .I7(I7),
    .S2(S2),
    .S1(S1),
    .S0(S0),
    .Y(Y)
);

initial begin

    $dumpfile("mux8to1.vcd");
    $dumpvars(0, mux8to1_tb);

    $display("S2 S1 S0 | Y");
    $monitor("%b  %b  %b | %b", S2, S1, S0, Y);

    // Fixed input values
    I0 = 0;
    I1 = 1;
    I2 = 0;
    I3 = 1;
    I4 = 1;
    I5 = 0;
    I6 = 1;
    I7 = 0;

    // Test all select combinations
    S2 = 0; S1 = 0; S0 = 0;
    #10 S2 = 0; S1 = 0; S0 = 1;
    #10 S2 = 0; S1 = 1; S0 = 0;
    #10 S2 = 0; S1 = 1; S0 = 1;
    #10 S2 = 1; S1 = 0; S0 = 0;
    #10 S2 = 1; S1 = 0; S0 = 1;
    #10 S2 = 1; S1 = 1; S0 = 0;
    #10 S2 = 1; S1 = 1; S0 = 1;

    #10 $finish;

end

endmodule

mux8to1.vcd
$date
	Mon Jul 27 00:24:03 2026
$end
$version
	Icarus Verilog
$end
$timescale
	1ps
$end
$scope module mux8to1_tb $end
$var wire 1 ! Y $end
$var reg 1 " I0 $end
$var reg 1 # I1 $end
$var reg 1 $ I2 $end
$var reg 1 % I3 $end
$var reg 1 & I4 $end
$var reg 1 ' I5 $end
$var reg 1 ( I6 $end
$var reg 1 ) I7 $end
$var reg 1 * S0 $end
$var reg 1 + S1 $end
$var reg 1 , S2 $end
$scope module uut $end
$var wire 1 " I0 $end
$var wire 1 # I1 $end
$var wire 1 $ I2 $end
$var wire 1 % I3 $end
$var wire 1 & I4 $end
$var wire 1 ' I5 $end
$var wire 1 ( I6 $end
$var wire 1 ) I7 $end
$var wire 1 * S0 $end
$var wire 1 + S1 $end
$var wire 1 , S2 $end
$var reg 1 ! Y $end
$upscope $end
$upscope $end
$enddefinitions $end
#0
$dumpvars
0,
0+
0*
0)
1(
0'
1&
1%
0$
1#
0"
0!
$end
#10000
1!
1*
#20000
0!
0*
1+
#30000
1!
1*
#40000
0*
0+
1,
#50000
0!
1*
#60000
1!
0*
1+
#70000
0!
1*
