03-Encoder-Decoder/rtl/priority_encoder8to3.v
module priority_encoder8to3(
    input  I0,
    input  I1,
    input  I2,
    input  I3,
    input  I4,
    input  I5,
    input  I6,
    input  I7,
    output reg A,
    output reg B,
    output reg C
);

always @(*) begin
    if (I7)      {A,B,C} = 3'b111;
    else if (I6) {A,B,C} = 3'b110;
    else if (I5) {A,B,C} = 3'b101;
    else if (I4) {A,B,C} = 3'b100;
    else if (I3) {A,B,C} = 3'b011;
    else if (I2) {A,B,C} = 3'b010;
    else if (I1) {A,B,C} = 3'b001;
    else         {A,B,C} = 3'b000;
end

endmodule

03-Encoder-Decoder/tb/priority_encoder8to3_tb.v
`timescale 1ns/1ps

module priority_encoder8to3_tb;

reg I0, I1, I2, I3, I4, I5, I6, I7;
wire A, B, C;

priority_encoder8to3 uut (
    .I0(I0),
    .I1(I1),
    .I2(I2),
    .I3(I3),
    .I4(I4),
    .I5(I5),
    .I6(I6),
    .I7(I7),
    .A(A),
    .B(B),
    .C(C)
);

initial begin

    $dumpfile("priority_encoder8to3.vcd");
    $dumpvars(0, priority_encoder8to3_tb);

    $display("I7 I6 I5 I4 I3 I2 I1 I0 | A B C");

    $monitor("%b  %b  %b  %b  %b  %b  %b  %b | %b %b %b",
              I7, I6, I5, I4, I3, I2, I1, I0,
              A, B, C);

    // No input active
    {I7,I6,I5,I4,I3,I2,I1,I0} = 8'b00000000; #10;

    // Single active inputs
    {I7,I6,I5,I4,I3,I2,I1,I0} = 8'b00000001; #10; // I0
    {I7,I6,I5,I4,I3,I2,I1,I0} = 8'b00000010; #10; // I1
    {I7,I6,I5,I4,I3,I2,I1,I0} = 8'b00000100; #10; // I2
    {I7,I6,I5,I4,I3,I2,I1,I0} = 8'b00001000; #10; // I3
    {I7,I6,I5,I4,I3,I2,I1,I0} = 8'b00010000; #10; // I4
    {I7,I6,I5,I4,I3,I2,I1,I0} = 8'b00100000; #10; // I5
    {I7,I6,I5,I4,I3,I2,I1,I0} = 8'b01000000; #10; // I6
    {I7,I6,I5,I4,I3,I2,I1,I0} = 8'b10000000; #10; // I7

    // Multiple active inputs (priority check)
    {I7,I6,I5,I4,I3,I2,I1,I0} = 8'b00100100; #10; // I5 and I2 -> Output = 101
    {I7,I6,I5,I4,I3,I2,I1,I0} = 8'b01001000; #10; // I6 and I3 -> Output = 110
    {I7,I6,I5,I4,I3,I2,I1,I0} = 8'b10010010; #10; // I7, I4 and I1 -> Output = 111

    $finish;

end

endmodule

priority_encoder8to3.vcd
$date
	Fri Jul 31 20:54:58 2026
$end
$version
	Icarus Verilog
$end
$timescale
	1ps
$end
$scope module priority_encoder8to3_tb $end
$var wire 1 ! C $end
$var wire 1 " B $end
$var wire 1 # A $end
$var reg 1 $ I0 $end
$var reg 1 % I1 $end
$var reg 1 & I2 $end
$var reg 1 ' I3 $end
$var reg 1 ( I4 $end
$var reg 1 ) I5 $end
$var reg 1 * I6 $end
$var reg 1 + I7 $end
$scope module uut $end
$var wire 1 $ I0 $end
$var wire 1 % I1 $end
$var wire 1 & I2 $end
$var wire 1 ' I3 $end
$var wire 1 ( I4 $end
$var wire 1 ) I5 $end
$var wire 1 * I6 $end
$var wire 1 + I7 $end
$var reg 1 # A $end
$var reg 1 " B $end
$var reg 1 ! C $end
$upscope $end
$upscope $end
$enddefinitions $end
#0
$dumpvars
0+
0*
0)
0(
0'
0&
0%
0$
0#
0"
0!
$end
#10000
1$
#20000
1!
1%
0$
#30000
1"
0!
1&
0%
#40000
1!
1'
0&
#50000
1#
0"
0!
1(
0'
#60000
1!
1)
0(
#70000
1"
0!
1*
0)
#80000
1!
1+
0*
#90000
0"
0+
1)
1&
#100000
1"
0!
1*
0)
1'
0&
#110000
1!
1+
0*
1(
0'
1%
